gaea_operator/__init__.py
gaea_operator/components/__init__.py
gaea_operator/components/eval/__init__.py
gaea_operator/components/eval/codetr.py
gaea_operator/components/eval/convnext.py
gaea_operator/components/eval/ocrnet.py
gaea_operator/components/eval/ppyoloe_plus.py
gaea_operator/components/eval/repvit.py
gaea_operator/components/eval/resnet.py
gaea_operator/components/icafe/__init__.py
gaea_operator/components/icafe/icafe.py
gaea_operator/components/inference/__init__.py
gaea_operator/components/inference/inference.py
gaea_operator/components/package/__init__.py
gaea_operator/components/package/package.py
gaea_operator/components/train/__init__.py
gaea_operator/components/train/change_ocrnet.py
gaea_operator/components/train/change_ppyoloe_plus.py
gaea_operator/components/train/codetr.py
gaea_operator/components/train/convnext.py
gaea_operator/components/train/ocrnet.py
gaea_operator/components/train/ppyoloe_plus.py
gaea_operator/components/train/repvit.py
gaea_operator/components/train/resnet.py
gaea_operator/components/transform/__init__.py
gaea_operator/components/transform/change_ocrnet.py
gaea_operator/components/transform/change_ppyoloe_plus.py
gaea_operator/components/transform/codetr.py
gaea_operator/components/transform/convnext.py
gaea_operator/components/transform/ocrnet.py
gaea_operator/components/transform/ppyoloe_plus.py
gaea_operator/components/transform/repvit.py
gaea_operator/components/transform/resnet.py
gaea_operator/components/transform_eval/__init__.py
gaea_operator/components/transform_eval/transform_eval.py
gaea_operator/config/__init__.py
gaea_operator/config/config.py
gaea_operator/config/generate_transform_config.py
gaea_operator/config/modify_package_files.py
gaea_operator/config/update_parse.py
gaea_operator/config/update_pbtxt.py
gaea_operator/config/codetr/__init__.py
gaea_operator/config/codetr/codetr_config.py
gaea_operator/config/codetr/template/__init__.py
gaea_operator/config/codetr/template/deploy_parameter.yaml
gaea_operator-4.2.2.dist-info/METADATA
gaea_operator-4.2.2.dist-info/WHEEL
gaea_operator-4.2.2.dist-info/top_level.txt
gaea_operator-4.2.2.dist-info/RECORD
