Metadata-Version: 2.1
Name: gaea-operator
Version: 4.2.2
Summary: A common operator library to help with training neural networks.
Home-page: https://console.cloud.baidu-int.com/devops/icode/repos/baidu/mlops/gaea-operator/tree/master
Author: liuyawen03
Author-email: liuyawen03@baidu.com
License: MIT
Classifier: Programming Language :: Python
Classifier: Programming Language :: Python :: 3
Classifier: Programming Language :: Python :: 3.7
Classifier: Programming Language :: Python :: 3.8
Classifier: Programming Language :: Python :: 3.9
Requires-Python: >=3.8
Requires-Dist: terminaltables
Requires-Dist: numpy
Requires-Dist: astor
Requires-Dist: certifi
Requires-Dist: charset-normalizer
Requires-Dist: debugpy
Requires-Dist: decorator
Requires-Dist: idna
Requires-Dist: opt-einsum
Requires-Dist: protobuf
Requires-Dist: PyYAML
Requires-Dist: six
Requires-Dist: urllib3
Requires-Dist: pycocotools
Requires-Dist: jsonargparse
Requires-Dist: pywindmill (==1.0.0.2)
Requires-Dist: bcelogger (==1.2.0.4)
Requires-Dist: gaea-tracker (==1.2.0.8)
